homeinfotools/__init__.py
homeinfotools/exceptions.py
homeinfotools/functions.py
homeinfotools/logging.py
homeinfotools/os.py
homeinfotools/ssh.py
homeinfotools/systemd.py
homeinfotools/worker.py
homeinfotools/filetransfer/__init__.py
homeinfotools/filetransfer/argparse.py
homeinfotools/filetransfer/filetransfer.py
homeinfotools/filetransfer/main.py
homeinfotools/filetransfer/worker.py
homeinfotools/his/__init__.py
homeinfotools/his/errorhandler.py
homeinfotools/his/exceptions.py
homeinfotools/his/functions.py
homeinfotools/his/session.py
homeinfotools/query/__init__.py
homeinfotools/query/argparse.py
homeinfotools/query/functions.py
homeinfotools/query/main.py
homeinfotools/rpc/__init__.py
homeinfotools/rpc/argparse.py
homeinfotools/rpc/common.py
homeinfotools/rpc/exceptions.py
homeinfotools/rpc/main.py
homeinfotools/rpc/reboot.py
homeinfotools/rpc/runcmd.py
homeinfotools/rpc/sudo.py
homeinfotools/rpc/sysupgrade.py
homeinfotools/rpc/worker.py
homeinfotools-1.6.6.dist-info/LICENSE.txt
homeinfotools-1.6.6.dist-info/METADATA
homeinfotools-1.6.6.dist-info/WHEEL
homeinfotools-1.6.6.dist-info/entry_points.txt
homeinfotools-1.6.6.dist-info/top_level.txt
homeinfotools-1.6.6.dist-info/RECORD
