Metadata-Version: 2.1
Name: homeinfotools
Version: 1.6.6
Summary: Tools to manage HOMEINFO digital signge systems.
Home-page: https://github.com/homeinfogmbh/homeinfotools
Author: HOMEINFO - Digitale Informationssysteme GmbH
Author-email: info@homeinfo.de
Maintainer: Richard Neumann
Maintainer-email: r.neumann@homeinfo.de
License: GPLv3
Keywords: python HOMEINFO systems client
Platform: UNKNOWN
Requires-Python: >=3.8
License-File: LICENSE.txt
Requires-Dist: setproctitle
